{"SystemFlag":{"SkipInitialize":0,"KeepPlayerPuppet":1,"KeepBadStatusVisual":0,"RidingVehicle":0},"Segments":[{"Label":"Main","EntryPoint":0,"Count":14},{"Label":"heal","EntryPoint":14,"Count":9},{"Label":"heal_02","EntryPoint":23,"Count":9}],"ScriptLocal":["0","0:0","SE_01","SE_02","SE_03"],"ScriptLocalValue":[0,0,0,0,0],"Mnemonics":[{"label":"Main","mnemonic":"Nop","operands":{"iValues":[],"rValues":[],"sValues":[]},"type":1,"comment":""},{"label":"","mnemonic":"PlayBGM","operands":{"iValues":[27,1,0,0,0,0,0,0],"rValues":[0,0,0,0,0,0,0,0],"sValues":["","","","","","","",""]},"type":1,"comment":""},{"label":"","mnemonic":"Msg","operands":{"iValues":[0,0,0,0,0,0,0,0],"rValues":[0,0,0,0,0,0,0,0],"sValues":["E0057_00_239_a_01","","","","","","",""]},"type":1,"comment":""},{"label":"","mnemonic":"ColorFade","operands":{"iValues":[0,0,0,0,0,0,0,0],"rValues":[0,0,0,0,0,0,0,0],"sValues":["","","","","","","",""]},"type":1,"comment":""},{"label":"","mnemonic":"ColorFade","operands":{"iValues":[0,0,0,160,0,0,0,0],"rValues":[0.7,0,0,0,0,0,0,0],"sValues":["","","","","","","",""]},"type":1,"comment":""},{"label":"","mnemonic":"Call","operands":{"iValues":[14,0,0,0,0,0,0,0],"rValues":[0,0,0,0,0,0,0,0],"sValues":["","","","","","","",""]},"type":1,"comment":""},{"label":"","mnemonic":"Call","operands":{"iValues":[23,0,0,0,0,0,0,0],"rValues":[0,0,0,0,0,0,0,0],"sValues":["","","","","","","",""]},"type":1,"comment":""},{"label":"","mnemonic":"ColorFade","operands":{"iValues":[0,0,0,0,0,0,0,0],"rValues":[0.7,0,0,0,0,0,0,0],"sValues":["","","","","","","",""]},"type":1,"comment":""},{"label":"","mnemonic":"RemoveCondition","operands":{"iValues":[0,0,0,0,0,0,0,0],"rValues":[0,0,0,0,0,0,0,0],"sValues":["","","","","","","",""]},"type":1,"comment":""},{"label":"","mnemonic":"RecoveryHP","operands":{"iValues":[0,1,1,0,0,0,0,0],"rValues":[0,0,0,0,0,0,0,0],"sValues":["","","","","","","",""]},"type":1,"comment":""},{"label":"","mnemonic":"RecoveryMP","operands":{"iValues":[0,1,1,1,0,0,0,0],"rValues":[0,0,0,0,0,0,0,0],"sValues":["","","","","","","",""]},"type":1,"comment":""},{"label":"","mnemonic":"Msg","operands":{"iValues":[0,0,0,0,0,0,0,0],"rValues":[0,0,0,0,0,0,0,0],"sValues":["E0057_00_239_a_02","","","","","","",""]},"type":1,"comment":""},{"label":"","mnemonic":"EncountBoss","operands":{"iValues":[256,21,16,0,0,0,0,0],"rValues":[0,0,0,0,0,0,0,0],"sValues":["sc_e_0057_1","","","","","","",""]},"type":1,"comment":""},{"label":"","mnemonic":"Exit","operands":{"iValues":[0,0,0,0,0,0,0,0],"rValues":[0,0,0,0,0,0,0,0],"sValues":["","","","","","","",""]},"type":1,"comment":""},{"label":"heal","mnemonic":"Nop","operands":{"iValues":[],"rValues":[],"sValues":[]},"type":2,"comment":""},{"label":"","mnemonic":"SetPuppet","operands":{"iValues":[0,24,18,0,0,0,0,0],"rValues":[0,0,0,0,0,0,0,0],"sValues":["","","","","","","",""]},"type":2,"comment":""},{"label":"","mnemonic":"ExecPuppet","operands":{"iValues":[0,0,0,0,0,0,0,0],"rValues":[0,0,0,0,0,0,0,0],"sValues":["","","","","","","",""]},"type":2,"comment":""},{"label":"","mnemonic":"Return","operands":{"iValues":[0,0,0,0,0,0,0,0],"rValues":[0,0,0,0,0,0,0,0],"sValues":["","","","","","","",""]},"type":2,"comment":""},{"label":"heal_00","mnemonic":"Nop","operands":{"iValues":[],"rValues":[],"sValues":[]},"type":2,"comment":""},{"label":"","mnemonic":"SetPos","operands":{"iValues":[21,16,3,0,0,0,0,0],"rValues":[0,0,0,0,0,0,0,0],"sValues":["","","","","","","",""]},"type":2,"comment":""},{"label":"","mnemonic":"PlaySE","operands":{"iValues":[201,1,2,0,0,0,0,0],"rValues":[0,0,0,0,0,0,0,0],"sValues":["","","","","","","",""]},"type":2,"comment":""},{"label":"","mnemonic":"PlayAnim","operands":{"iValues":[0,1,0,0,0,0,0,0],"rValues":[1,0,0,0,0,0,0,0],"sValues":["","","","","","","",""]},"type":2,"comment":""},{"label":"","mnemonic":"Exit","operands":{"iValues":[0,0,0,0,0,0,0,0],"rValues":[0,0,0,0,0,0,0,0],"sValues":["","","","","","","",""]},"type":2,"comment":""},{"label":"heal_02","mnemonic":"Nop","operands":{"iValues":[],"rValues":[],"sValues":[]},"type":2,"comment":""},{"label":"","mnemonic":"SetPuppet","operands":{"iValues":[0,19,27,0,0,0,0,0],"rValues":[0,0,0,0,0,0,0,0],"sValues":["","","","","","","",""]},"type":2,"comment":""},{"label":"","mnemonic":"ExecPuppet","operands":{"iValues":[0,0,0,0,0,0,0,0],"rValues":[0,0,0,0,0,0,0,0],"sValues":["","","","","","","",""]},"type":2,"comment":""},{"label":"","mnemonic":"Return","operands":{"iValues":[0,0,0,0,0,0,0,0],"rValues":[0,0,0,0,0,0,0,0],"sValues":["","","","","","","",""]},"type":2,"comment":""},{"label":"heal_02_00","mnemonic":"Nop","operands":{"iValues":[],"rValues":[],"sValues":[]},"type":2,"comment":""},{"label":"","mnemonic":"SetPos","operands":{"iValues":[21,17,3,0,0,0,0,0],"rValues":[0,0,0,0,0,0,0,0],"sValues":["","","","","","","",""]},"type":2,"comment":""},{"label":"","mnemonic":"PlaySE","operands":{"iValues":[204,1,3,0,0,0,0,0],"rValues":[0,0,0,0,0,0,0,0],"sValues":["","","","","","","",""]},"type":2,"comment":""},{"label":"","mnemonic":"PlayAnim","operands":{"iValues":[0,1,0,0,0,0,0,0],"rValues":[1,0,0,0,0,0,0,0],"sValues":["","","","","","","",""]},"type":2,"comment":""},{"label":"","mnemonic":"Exit","operands":{"iValues":[0,0,0,0,0,0,0,0],"rValues":[0,0,0,0,0,0,0,0],"sValues":["","","","","","","",""]},"type":2,"comment":""}],"Animations":[],"Name":"sc_e_0057","Title":{"main":"ルビカンテと戦う","sub":"オンラクのデモ"}}